platetrack/__init__.py
platetrack/_io.py
platetrack/dock_widgets.py
platetrack/napari.yaml
platetrack/platelet_info.py
platetrack-0.0.7.dist-info/LICENSE
platetrack-0.0.7.dist-info/METADATA
platetrack-0.0.7.dist-info/WHEEL
platetrack-0.0.7.dist-info/entry_points.txt
platetrack-0.0.7.dist-info/top_level.txt
platetrack-0.0.7.dist-info/RECORD
