Metadata-Version: 2.1
Name: platetrack
Version: 0.0.7
Summary: napari plugin for tracking platelets with trackpy
Home-page: https://github.com/AbigailMcGovern/platelet-tracking
Author: Abigail S McGovern
Author-email: abigail_mcgovern@hotmail.com
License: BSD-3-Clause
Project-URL: Bug Tracker, https://github.com/abigailmcgovern/platelet-tracking/issues
Project-URL: Documentation, https://github.com/abigailmcgovern/platelet-tracking#README.md
Project-URL: Source Code, https://github.com/abigailmcgovern/platelet-tracking
Project-URL: User Support, https://github.com/abigailmcgovern/platelet-tracking/issues
Classifier: Framework :: napari
Classifier: Programming Language :: Python
Classifier: Programming Language :: Python :: 3
Classifier: Programming Language :: Python :: 3.9
Classifier: Programming Language :: Python :: 3.10
Classifier: Programming Language :: Python :: 3.11
Classifier: Operating System :: OS Independent
Classifier: License :: OSI Approved :: BSD License
Classifier: Intended Audience :: Science/Research
Classifier: Topic :: Scientific/Engineering
Classifier: Topic :: Scientific/Engineering :: Image Processing
Requires-Python: >=3.7
License-File: LICENSE
Requires-Dist: napari
Requires-Dist: numpy
Requires-Dist: trackpy
Requires-Dist: pandas
Requires-Dist: plateletanalysis
